[
  {
    "id": "MFR-001",
    "name": "Ford Motor Company",
    "logoUrl": "https://raw.githubusercontent.com/yourusername/car-api/main/images/ford-logo.jpg",
    "foundedYear": 1903,
    "headquarters": "Dearborn, Michigan, USA",
    "country": "United States"
  },
  {
    "id": "MFR-002",
    "name": "Tesla Inc.",
    "logoUrl": "https://raw.githubusercontent.com/yourusername/car-api/main/images/tesla-logo.jpg",
    "foundedYear": 2003,
    "headquarters": "Austin, Texas, USA",
    "country": "United States"
  },
  {
    "id": "MFR-003",
    "name": "Porsche AG",
    "logoUrl": "https://raw.githubusercontent.com/yourusername/car-api/main/images/porsche-logo.jpg",
    "foundedYear": 1931,
    "headquarters": "Stuttgart, Germany",
    "country": "Germany"
  },
  {
    "id": "MFR-004",
    "name": "Toyota Motor Corporation",
    "logoUrl": "https://raw.githubusercontent.com/yourusername/car-api/main/images/toyota-logo.jpg",
    "foundedYear": 1937,
    "headquarters": "Toyota City, Japan",
    "country": "Japan"
  },
  {
    "id": "MFR-005",
    "name": "BMW Group",
    "logoUrl": "https://raw.githubusercontent.com/yourusername/car-api/main/images/bmw-logo.jpg",
    "foundedYear": 1916,
    "headquarters": "Munich, Germany",
    "country": "Germany"
  },
  {
    "id": "MFR-006",
    "name": "General Motors",
    "logoUrl": "https://raw.githubusercontent.com/yourusername/car-api/main/images/gm-logo.jpg",
    "foundedYear": 1908,
    "headquarters": "Detroit, Michigan, USA",
    "country": "United States"
  },
  {
    "id": "MFR-007",
    "name": "Audi AG",
    "logoUrl": "https://raw.githubusercontent.com/yourusername/car-api/main/images/audi-logo.jpg",
    "foundedYear": 1909,
    "headquarters": "Ingolstadt, Germany",
    "country": "Germany"
  },
  {
    "id": "MFR-008",
    "name": "Honda Motor Co.",
    "logoUrl": "https://raw.githubusercontent.com/yourusername/car-api/main/images/honda-logo.jpg",
    "foundedYear": 1948,
    "headquarters": "Tokyo, Japan",
    "country": "Japan"
  },
  {
    "id": "MFR-009",
    "name": "Mercedes-Benz Group AG",
    "logoUrl": "https://raw.githubusercontent.com/yourusername/car-api/main/images/mercedes-logo.jpg",
    "foundedYear": 1926,
    "headquarters": "Stuttgart, Germany",
    "country": "Germany"
  },
  {
    "id": "MFR-010",
    "name": "Mazda Motor Corporation",
    "logoUrl": "https://raw.githubusercontent.com/yourusername/car-api/main/images/mazda-logo.jpg",
    "foundedYear": 1920,
    "headquarters": "Hiroshima, Japan",
    "country": "Japan"
  },
  {
    "id": "MFR-011",
    "name": "Lamborghini S.p.A.",
    "logoUrl": "https://raw.githubusercontent.com/yourusername/car-api/main/images/lamborghini-logo.jpg",
    "foundedYear": 1963,
    "headquarters": "Sant'Agata Bolognese, Italy",
    "country": "Italy"
  },
  {
    "id": "MFR-012",
    "name": "Nissan Motor Corporation",
    "logoUrl": "https://raw.githubusercontent.com/yourusername/car-api/main/images/nissan-logo.jpg",
    "foundedYear": 1933,
    "headquarters": "Yokohama, Japan",
    "country": "Japan"
  }
]
